setup.py
horse_lastfm/__init__.py
horse_lastfm/bridles.py
horse_lastfm/models.py
horse_lastfm.egg-info/PKG-INFO
horse_lastfm.egg-info/SOURCES.txt
horse_lastfm.egg-info/dependency_links.txt
horse_lastfm.egg-info/requires.txt
horse_lastfm.egg-info/top_level.txt